{"name":"t:sections.header.name","type":"header","sections":{"header":{"type":"header","disabled":true,"settings":{"color_scheme":"background-1","logo_position":"middle-left","menu":"","menu_type_desktop":"dropdown","sticky_header_type":"none","show_line_separator":false,"mobile_logo_position":"center","margin_bottom":0,"padding_top":0,"padding_bottom":0}},"235bd67a-dcfe-4754-87b5-677ed039b477":{"type":"os-header","custom_css":[".osh-lvl1-link {font-family: \"Moniqa-Condensed\"; font-size: 20px; font-weight: normal;}",".osh-lvl2-title {font-family: \"Moniqa-Condensed\"; font-size: 15pt; font-weight: normal;}",".osh-lvl3-link {font-family: \"Gill Sans\"; font-size: 14pt; display: block; text-transform: lowercase;}",".osh-lvl3-link:first-line {text-transform: capitalize;}","@media (max-width: 1387px) {.osh-lvl1-link {font-size: 20pt; }}","@media (max-width: 1280px) {.osh-lvl1-link {font-size: 16.22px; }}","@media (max-width: 1027px) {.osh-lvl1-link {font-size: 14.11px; }}"],"settings":{"logo":"shopify:\/\/shop_images\/output-onlinegiftools.gif","logo_height":7,"menu":"new-header-menu-2","margin_top":0,"margin_bottom":0,"padding_top":0.1,"padding_bottom":0}},"bac20a47-243b-4de2-8104-26e79def1d0b":{"type":"new-marquee","blocks":{"6385bc2c-cddc-4aed-86ef-966a26c0296d":{"type":"marquee_strip","settings":{"text":"Free U.S. Shipping On Orders $550+"}},"1195d4bb-a88b-4ba1-a229-b2b4da638de8":{"type":"marquee_strip","settings":{"text":"WORLDWIDE DELIVERY"}},"2fa72076-570c-445e-aa91-094bb8891719":{"type":"marquee_strip","settings":{"text":"Free U.K. Shipping On Orders £500+"}},"marquee_strip_NKHfVV":{"type":"marquee_strip","settings":{"text":"EXPRESS SHIPPING AVAILABLE ON ALL READY TO SHIP ITEMS"}},"f2deefe3-0c81-49be-98c7-7d1e0a887437":{"type":"marquee_strip","disabled":true,"settings":{"text":"BLACK FRIDAY SALE - SHOP 25% OFF EVERYTHING"}},"9fd81593-7afc-4689-964d-2ccc9c499e1f":{"type":"marquee_strip","disabled":true,"settings":{"text":"DISCOUNT AUTOMATICALLY APPLIES AT CHECKOUT"}},"64ae98cc-9a39-4518-8341-2ddee9758571":{"type":"marquee_strip","disabled":true,"settings":{"text":"CYBER MONDAY SALE - BUY 3 GET 1 FREE ON ANY ITEM"}},"f48fc052-c047-4770-a380-0ddcd6f06eb5":{"type":"marquee_strip","disabled":true,"settings":{"text":"LIMITED TIME ONLY OFFER"}}},"block_order":["6385bc2c-cddc-4aed-86ef-966a26c0296d","1195d4bb-a88b-4ba1-a229-b2b4da638de8","2fa72076-570c-445e-aa91-094bb8891719","marquee_strip_NKHfVV","f2deefe3-0c81-49be-98c7-7d1e0a887437","9fd81593-7afc-4689-964d-2ccc9c499e1f","64ae98cc-9a39-4518-8341-2ddee9758571","f48fc052-c047-4770-a380-0ddcd6f06eb5"],"custom_css":["* {font-family: \"Gill Sans\"; font-size: 9pt; font-style: normal; font-weight: normal;}"],"settings":{"heading":"","subheading":"","bg":"#faeadc","bg_opacity":1,"text_color":"#000000","mobile_font_size":14,"desktop_font_size":14,"mobile_padding":0,"desktop_padding":0,"mobile_text_spacing":0.5,"desktop_text_spacing":0.5,"margin_botton":0,"speed":140,"direction":"left","toggle_pause_on_hover":false,"capitalise_text":true,"emoji":"","gap":1,"mobile_gap":1}}},"order":["header","235bd67a-dcfe-4754-87b5-677ed039b477","bac20a47-243b-4de2-8104-26e79def1d0b"]}